ota/__init__.py
ota/main.py
ota/cli/__init__.py
ota/cli/analyze.py
ota/cli/config.py
ota/cli/download.py
ota/cli/inspect.py
ota/cli/send.py
ota/core/__init__.py
ota/core/analyze.py
ota/core/console.py
ota/core/models.py
ota/core/rpc.py
ota/core/settings.py
ota/core/tools.py
ota/odoo/__init__.py
ota/odoo/field.py
ota/odoo/model.py
ota/odoo/module.py
odoo_technical_analysis-0.1.8.dist-info/METADATA
odoo_technical_analysis-0.1.8.dist-info/WHEEL
odoo_technical_analysis-0.1.8.dist-info/entry_points.txt
odoo_technical_analysis-0.1.8.dist-info/top_level.txt
odoo_technical_analysis-0.1.8.dist-info/RECORD
